[
  {
    "price": 87,
    "name": "Holiday Inn Express Hotel \u0026 Suites Belgrade",
    "address": "309 W Madison Ave, Belgrade, MT, 59714 United States",
    "distance": 1.1,
    "rating": 4.5,
    "imgUrl": "https://exp.cdn-hotels.com/hotels/7000000/6230000/6228100/6228065/6228065_181_l.jpg"
  },
  {
    "price": 51,
    "name": "Super 8 Belgrade / Bozeman Airport",
    "address": "6450 Jackrabbit Ln, Belgrade, MT, 59714 United States",
    "distance": 1.7,
    "rating": 4.0,
    "imgUrl": "https://exp.cdn-hotels.com/hotels/1000000/970000/968600/968517/d36dc983_l.jpg"
  },
  {
    "price": 79,
    "name": "La Quinta Inn \u0026 Suites Belgrade / Bozeman Airport",
    "address": "6445 Jackrabbit Ln, Belgrade, MT, 59714 United States",
    "distance": 1.7,
    "rating": 4.0,
    "imgUrl": "https://exp.cdn-hotels.com/hotels/1000000/860000/852700/852650/b320fe33_l.jpg"
  },
  {
    "price": 59,
    "name": "Quality Inn",
    "address": "6261 Jackrabbit Ln, Belgrade, MT, 59714 United States",
    "distance": 1.9,
    "rating": 4.0,
    "imgUrl": "https://exp.cdn-hotels.com/hotels/1000000/300000/292800/292712/ecb7bef8_l.jpg"
  },
  {
    "price": 84,
    "name": "Whispering Pines Guest Suites",
    "address": "67 Village Drive, Belgrade, MT, 59714 United States",
    "distance": 2.1,
    "rating": 4.8,
    "imgUrl": "https://exp.cdn-hotels.com/hotels/16000000/15800000/15795300/15795260/33f71ab3_l.jpg"
  }
]