[
  {
    "price": 142,
    "name": "Menger Hotel",
    "address": "204 Alamo Plaza, San Antonio, TX, 78205 United States",
    "distance": 0.1,
    "rating": 4.0,
    "imgUrl": "https://exp.cdn-hotels.com/hotels/1000000/10000/5900/5877/41cb9b6d_l.jpg"
  },
  {
    "price": 212,
    "name": "Hilton Palacio Del Rio",
    "address": "200 S Alamo St, San Antonio, TX, 78205 United States",
    "distance": 0.1,
    "rating": 4.5,
    "imgUrl": "https://exp.cdn-hotels.com/hotels/1000000/30000/25600/25575/25575_93_l.jpg"
  },
  {
    "price": 157,
    "name": "Crockett Hotel",
    "address": "320 Bonham, San Antonio, TX, 78205 United States",
    "distance": 0.1,
    "rating": 4.0,
    "imgUrl": "https://exp.cdn-hotels.com/hotels/1000000/10000/1600/1534/1534_92_l.jpg"
  },
  {
    "price": 199,
    "name": "Hotel Contessa - Luxury Suites on the Riverwalk",
    "address": "306 W Market Street, San Antonio, TX, 78205 United States",
    "distance": 0.2,
    "rating": 4.5,
    "imgUrl": "https://exp.cdn-hotels.com/hotels/2000000/1240000/1234400/1234369/1234369_179_l.jpg"
  },
  {
    "price": 225,
    "name": "Grand Hyatt San Antonio",
    "address": "600 E Market St, San Antonio, TX, 78205 United States",
    "distance": 0.2,
    "rating": 4.5,
    "imgUrl": "https://exp.cdn-hotels.com/hotels/2000000/1850000/1848300/1848212/43613d9b_l.jpg"
  },
  {
    "price": 282,
    "name": "Marriott San Antonio Riverwalk",
    "address": "889 East Market Street, San Antonio, TX, 78205 United States",
    "distance": 0.2,
    "rating": 4.0,
    "imgUrl": "https://exp.cdn-hotels.com/hotels/1000000/30000/23100/23033/23033_105_l.jpg"
  },
  {
    "price": 258,
    "name": "The Westin Riverwalk, San Antonio",
    "address": "420 W Market St, San Antonio, TX, 78205 United States",
    "distance": 0.2,
    "rating": 4.5,
    "imgUrl": "https://exp.cdn-hotels.com/hotels/1000000/340000/330600/330528/330528_264_l.jpg"
  },
  {
    "price": 159,
    "name": "The Emily Morgan San Antonio - a DoubleTree by Hilton Hotel",
    "address": "705 E Houston St, San Antonio, TX, 78205 United States",
    "distance": 0.2,
    "rating": 4.5,
    "imgUrl": "https://exp.cdn-hotels.com/hotels/1000000/10000/3000/2916/2916_237_l.jpg"
  },
  {
    "price": 269,
    "name": "Mokara Hotel \u0026 Spa San Antonio",
    "address": "212 W Crockett Street, San Antonio, TX, 78205 United States",
    "distance": 0.2,
    "rating": 4.5,
    "imgUrl": "https://exp.cdn-hotels.com/hotels/1000000/990000/988500/988490/988490_37_l.jpg"
  },
  {
    "price": 120,
    "name": "Hotel Indigo Downtown-Alamo",
    "address": "105 N Alamo, San Antonio, TX, 78205 United States",
    "distance": 0.2,
    "rating": 4.0,
    "imgUrl": "https://exp.cdn-hotels.com/hotels/3000000/2240000/2239900/2239843/2239843_216_l.jpg"
  }
]