[
  {
    "price": 101,
    "name": "Holiday Inn Express \u0026 Suites, Lake Elsinore",
    "address": "31573 Canyon Estates Dr, Lake Elsinore, CA, 92532 United States",
    "distance": 4.1,
    "rating": 4.0,
    "imgUrl": "https://exp.cdn-hotels.com/hotels/3000000/2200000/2193200/2193180/2193180_148_l.jpg"
  },
  {
    "price": 91,
    "name": "Best Western Plus Lake Elsinore Inn \u0026 Suites",
    "address": "31781 Casino Drive, Lake Elsinore, CA, 92530 United States",
    "distance": 4.1,
    "rating": 4.0,
    "imgUrl": "https://exp.cdn-hotels.com/hotels/2000000/1740000/1738500/1738455/1738455_48_l.jpg"
  },
  {
    "price": 112,
    "name": "Quality Inn Lake Elsinore I-15",
    "address": "31808 Casino Dr, Lake Elsinore, CA, 92530 United States",
    "distance": 4.2,
    "rating": 3.5,
    "imgUrl": "https://exp.cdn-hotels.com/hotels/2000000/1510000/1509800/1509736/1509736_73_l.jpg"
  },
  {
    "price": 78,
    "name": "Econo Lodge Lake Elsinore Casino",
    "address": "20930 Malaga Rd, Lake Elsinore, CA, 92530 United States",
    "distance": 4.2,
    "rating": 3.5,
    "imgUrl": ""
  }
]