[
  {
    "price": 102,
    "name": "Days Inn Concord",
    "address": "5370 Clayton Rd, Concord, CA, 94521 United States",
    "distance": 1.5,
    "rating": 3.5,
    "imgUrl": "https://exp.cdn-hotels.com/hotels/1000000/20000/17300/17267/147e6526_l.jpg"
  },
  {
    "price": 120,
    "name": "Best Western Heritage Inn",
    "address": "4600 Clayton Rd, Concord, CA, 94521 United States",
    "distance": 3.1,
    "rating": 3.5,
    "imgUrl": "https://exp.cdn-hotels.com/hotels/1000000/30000/21200/21183/5f3251ce_l.jpg"
  },
  {
    "price": 95,
    "name": "Americas Best Value Inn",
    "address": "3555 Clayton Road, Concord, CA, 94519 United States",
    "distance": 4.6,
    "rating": 2.0,
    "imgUrl": "https://exp.cdn-hotels.com/hotels/2000000/1760000/1753400/1753361/1753361_51_l.jpg"
  },
  {
    "price": 70,
    "name": "Motel 6 Pittsburg",
    "address": "2101 Loveridge Rd, Pittsburg, CA, 94565 United States",
    "distance": 5.6,
    "rating": 2.0,
    "imgUrl": "https://exp.cdn-hotels.com/hotels/1000000/1000000/996400/996349/996349_54_l.jpg"
  },
  {
    "price": 112,
    "name": "Hampton Inn \u0026 Suites Pittsburg",
    "address": "1201 California Ave, Pittsburg, CA, 94565 United States",
    "distance": 5.7,
    "rating": 4.5,
    "imgUrl": "https://exp.cdn-hotels.com/hotels/2000000/1880000/1876400/1876345/1876345_10_l.jpg"
  },
  {
    "price": 106,
    "name": "Studio 6 Concord",
    "address": "1370 Monument Blvd, I-680 at Monument Blvd, Concord, CA, 94520 United States",
    "distance": 6.3,
    "rating": 2.5,
    "imgUrl": "https://exp.cdn-hotels.com/hotels/1000000/10000/5600/5581/1f86c475_l.jpg"
  },
  {
    "price": 65,
    "name": "Premier Inns Concord",
    "address": "1581 Concord Avenue, Concord, CA, 94520 United States",
    "distance": 6.3,
    "rating": 2.5,
    "imgUrl": "https://exp.cdn-hotels.com/hotels/14000000/13280000/13279000/13278954/241fcae5_l.jpg"
  },
  {
    "price": 214,
    "name": "Residence Inn by Marriott Pleasant Hill",
    "address": "700 Ellinwood Way, Pleasant Hill, CA, 94523 United States",
    "distance": 6.9,
    "rating": 4.0,
    "imgUrl": "https://exp.cdn-hotels.com/hotels/1000000/10000/1400/1302/89eb2760_l.jpg"
  },
  {
    "price": 184,
    "name": "Hilton Concord",
    "address": "1970 Diamond Blvd, Concord, CA, 94520 United States",
    "distance": 6.9,
    "rating": 4.0,
    "imgUrl": "https://exp.cdn-hotels.com/hotels/1000000/10000/300/260/260_113_l.jpg"
  },
  {
    "price": 274,
    "name": "Renaissance Clubsport Walnut Creek Hotel",
    "address": "2805 Jones Rd, Walnut Creek, CA, 94597 United States",
    "distance": 6.9,
    "rating": 4.5,
    "imgUrl": "https://exp.cdn-hotels.com/hotels/1000000/900000/891300/891251/a46de72e_l.jpg"
  }
]