[
  {
    "price": 169,
    "name": "Seabonay Beach Resort",
    "address": "1159 Hillsboro Mile, Hillsboro Beach, FL, 33062 United States",
    "distance": 1.4,
    "rating": 3.5,
    "imgUrl": "https://exp.cdn-hotels.com/hotels/1000000/430000/425500/425451/425451_87_l.jpg"
  },
  {
    "price": 179,
    "name": "La Costa Beach Club",
    "address": "1504 North Ocean Boulevard, Pompano Beach, FL, 33062 United States",
    "distance": 1.6,
    "rating": 4.0,
    "imgUrl": "https://exp.cdn-hotels.com/hotels/5000000/4160000/4155500/4155443/4155443_17_l.jpg"
  },
  {
    "price": 350,
    "name": "Residence Inn Fort Lauderdale Pompano Beach / Oceanfront",
    "address": "1350 N Ocean Blvd, Pompano Beach, FL, 33062 United States",
    "distance": 1.7,
    "rating": 4.0,
    "imgUrl": "https://exp.cdn-hotels.com/hotels/1000000/40000/34300/34266/34266_120_l.jpg"
  },
  {
    "price": 94,
    "name": "Mid Mari by Real Estate Gizmo",
    "address": "3230 NE 13th Street, Unit 108, Pompano Beach, FL, 33062 United States",
    "distance": 1.8,
    "rating": 0.0,
    "imgUrl": "https://exp.cdn-hotels.com/hotels/17000000/16640000/16637700/16637657/b146d1c2_l.jpg"
  },
  {
    "price": 275,
    "name": "Fort Lauderdale Marriott Pompano Beach Resort and Spa",
    "address": "1200 North Ocean Blvd, Pompano Beach, FL, 33062 United States",
    "distance": 1.9,
    "rating": 4.0,
    "imgUrl": "https://exp.cdn-hotels.com/hotels/6000000/5830000/5820300/5820293/5820293_15_l.jpg"
  },
  {
    "price": 109,
    "name": "Sea horse Motel",
    "address": "901 N Ocean Blvd, Pompano Beach, FL, 33062 United States",
    "distance": 2.0,
    "rating": 4.5,
    "imgUrl": "https://exp.cdn-hotels.com/hotels/11000000/10980000/10975300/10975276/a64873bb_l.jpg"
  },
  {
    "price": 139,
    "name": "Beach Bright Inn",
    "address": "906 N. Riverside Dr, Pompano Beach, FL, 33062 United States",
    "distance": 2.0,
    "rating": 3.7,
    "imgUrl": "https://exp.cdn-hotels.com/hotels/14000000/13400000/13390800/13390757/13390757_12_l.jpg"
  },
  {
    "price": 127,
    "name": "Ocean View Condo by Real Estate Gizmo",
    "address": "900 North Ocean Blvd, unit 32, Pompano Beach, FL, 33062 United States",
    "distance": 2.0,
    "rating": 0.0,
    "imgUrl": "https://exp.cdn-hotels.com/hotels/17000000/16640000/16637300/16637276/38a7342f_l.jpg"
  },
  {
    "price": 139,
    "name": "The Pelican\u0027s Nest",
    "address": "3204 Northeast 9th Street, Pompano Beach, FL, 33062 United States",
    "distance": 2.0,
    "rating": 3.7,
    "imgUrl": "https://exp.cdn-hotels.com/hotels/14000000/13400000/13390800/13390725/13390725_2_l.jpg"
  },
  {
    "price": 149,
    "name": "Budget Lodge",
    "address": "831 North Ocean Blvd, Pompano Beach, FL, 33062 United States",
    "distance": 2.0,
    "rating": 3.5,
    "imgUrl": "https://exp.cdn-hotels.com/hotels/11000000/11000000/10994200/10994176/10994176_6_l.jpg"
  }
]