[
  {
    "price": 91,
    "name": "Econo Lodge Douglassville",
    "address": "387 Ben Franklin Hwy W, Douglassville, PA, 19518 United States",
    "distance": 4.1,
    "rating": 3.5,
    "imgUrl": "https://exp.cdn-hotels.com/hotels/1000000/30000/21200/21107/21107_34_l.jpg"
  },
  {
    "price": 76,
    "name": "Motel 6 Pottstown",
    "address": "78 Robinson St, Pottstown, PA, 19464 United States",
    "distance": 7.5,
    "rating": 2.5,
    "imgUrl": "https://exp.cdn-hotels.com/hotels/2000000/1050000/1040800/1040739/1040739_6_l.jpg"
  },
  {
    "price": 109,
    "name": "Comfort Inn \u0026 Suites Pottstown - Limerick",
    "address": "99 Robinson Street, Pottstown, PA, 19464 United States",
    "distance": 7.5,
    "rating": 4.0,
    "imgUrl": "https://exp.cdn-hotels.com/hotels/1000000/30000/21900/21846/21846_93_l.jpg"
  },
  {
    "price": 85,
    "name": "Quality Inn Pottstown",
    "address": "61 W King St, Pottstown, PA, 19464 United States",
    "distance": 7.7,
    "rating": 3.5,
    "imgUrl": "https://exp.cdn-hotels.com/hotels/1000000/790000/788400/788399/a54fe381_l.jpg"
  },
  {
    "price": 68,
    "name": "Americas Best Value Inn",
    "address": "29 E High Street, Pottstown, PA, 19464 United States",
    "distance": 7.8,
    "rating": 1.5,
    "imgUrl": "https://exp.cdn-hotels.com/hotels/1000000/30000/26600/26546/26546_29_l.jpg"
  },
  {
    "price": 73,
    "name": "Red Carpet Inn \u0026 Suites Morgantown",
    "address": "3736 Main Street, Morgantown, Pennsylvania, 19543 United States",
    "distance": 7.9,
    "rating": 1.5,
    "imgUrl": "https://exp.cdn-hotels.com/hotels/1000000/910000/903400/903352/903352_12_l.jpg"
  },
  {
    "price": 112,
    "name": "Doubletree By Hilton Reading",
    "address": "701 Penn Street, Reading, PA, 19601 United States",
    "distance": 8.4,
    "rating": 5.0,
    "imgUrl": "https://exp.cdn-hotels.com/hotels/12000000/11920000/11919200/11919132/aff64385_l.jpg"
  },
  {
    "price": 95,
    "name": "Candlewood Suites Reading",
    "address": "55 S 3rd Ave, Reading, PA, 19611 United States",
    "distance": 9.2,
    "rating": 4.0,
    "imgUrl": "https://exp.cdn-hotels.com/hotels/3000000/2300000/2292900/2292858/2292858_140_l.jpg"
  },
  {
    "price": 64,
    "name": "Country Inn Motel",
    "address": "330 E Wyomissing Avenue, Mohnton, PA, 19540 United States",
    "distance": 9.6,
    "rating": 3.0,
    "imgUrl": "https://exp.cdn-hotels.com/hotels/3000000/2590000/2589500/2589470/2589470_6_l.jpg"
  },
  {
    "price": 76,
    "name": "Days Inn Pottstown",
    "address": "1600 Industrial Highway, Pottstown, PA, 19464 United States",
    "distance": 9.7,
    "rating": 3.0,
    "imgUrl": "https://exp.cdn-hotels.com/hotels/1000000/10000/1700/1618/1618_200_l.jpg"
  }
]