[
  {
    "price": 99,
    "name": "Hampton Inn Saco Orchard",
    "address": "48 Industrial Park Rd, Saco, ME, 04072 United States",
    "distance": 1.1,
    "rating": 4.5,
    "imgUrl": "https://exp.cdn-hotels.com/hotels/1000000/550000/544100/544032/544032_4_l.jpg"
  },
  {
    "price": 61,
    "name": "Rodeway Inn Saco",
    "address": "21 Ocean Park Rd, Saco, ME, 04072 United States",
    "distance": 1.2,
    "rating": 3.0,
    "imgUrl": "https://exp.cdn-hotels.com/hotels/2000000/1100000/1094500/1094412/1094412_45_l.jpg"
  },
  {
    "price": 39,
    "name": "Exit 5 Motel \u0026 Cottages",
    "address": "18 Ocean Park Rd, Saco, ME, 04072 United States",
    "distance": 1.2,
    "rating": 3.0,
    "imgUrl": "https://exp.cdn-hotels.com/hotels/3000000/2140000/2133800/2133757/2133757_39_l.jpg"
  },
  {
    "price": 85,
    "name": "Ramada Saco/Old Orchard Beach Area",
    "address": "352 North St, Saco, ME, 04072 United States",
    "distance": 1.9,
    "rating": 4.0,
    "imgUrl": "https://exp.cdn-hotels.com/hotels/1000000/330000/327900/327816/d75d4344_l.jpg"
  },
  {
    "price": 89,
    "name": "Americas Best Value Inn - Mt. Royal",
    "address": "30 W. Grand Ave., Old Orchard Beach, ME, 04064 United States",
    "distance": 2.5,
    "rating": 3.5,
    "imgUrl": "https://exp.cdn-hotels.com/hotels/1000000/560000/558700/558601/558601_102_l.jpg"
  }
]