[
  {
    "price": 80,
    "name": "Americas Best Value Inn",
    "address": "128 Cheekwood Lane, Ullin, IL, 62992 United States",
    "distance": 14.0,
    "rating": 4.0,
    "imgUrl": "https://exp.cdn-hotels.com/hotels/1000000/20000/17200/17193/17193_124_l.jpg"
  },
  {
    "price": 72,
    "name": "Laketree Inn And Suites Marion",
    "address": "9600 Lake Of Egypt Rd, Marion, IL, 62959 United States",
    "distance": 19.0,
    "rating": 3.5,
    "imgUrl": "https://exp.cdn-hotels.com/hotels/5000000/4080000/4071700/4071695/28a7a376_l.jpg"
  },
  {
    "price": 61,
    "name": "Super 8 Carbondale",
    "address": "1180 E Main St, Carbondale, IL, 62901 United States",
    "distance": 19.0,
    "rating": 3.5,
    "imgUrl": "https://exp.cdn-hotels.com/hotels/1000000/440000/439700/439693/439693_108_l.jpg"
  },
  {
    "price": 103,
    "name": "Best Western Saluki Inn",
    "address": "801 N Giant City Rd, Carbondale, IL, 62902 United States",
    "distance": 19.0,
    "rating": 4.5,
    "imgUrl": "https://exp.cdn-hotels.com/hotels/1000000/120000/119200/119178/119178_178_l.jpg"
  },
  {
    "price": 129,
    "name": "Hampton Inn Carbondale",
    "address": "2175 Reed Station Pkwy, Carbondale, IL, 62901 United States",
    "distance": 20.0,
    "rating": 4.0,
    "imgUrl": "https://exp.cdn-hotels.com/hotels/1000000/480000/479200/479116/5fb6118b_l.jpg"
  },
  {
    "price": 134,
    "name": "Holiday Inn Carbondale-Conference Center",
    "address": "2300 Reed Station Parkway, Carbondale, IL, 62901 United States",
    "distance": 20.0,
    "rating": 4.0,
    "imgUrl": "https://exp.cdn-hotels.com/hotels/2000000/1490000/1489300/1489254/1489254_110_l.jpg"
  },
  {
    "price": 144,
    "name": "Holiday Inn Express Hotel \u0026 Suites Cape Girardeau I-55",
    "address": "3253 William Street, Cape Girardeau, MO, 63701 United States",
    "distance": 22.0,
    "rating": 4.5,
    "imgUrl": "https://exp.cdn-hotels.com/hotels/2000000/1280000/1278600/1278542/1278542_214_l.jpg"
  },
  {
    "price": 65,
    "name": "Americas Best Value Inn-Murphysboro/Carbondale",
    "address": "128 E. Walnut Street, Murphysboro, IL, 62966 United States",
    "distance": 22.0,
    "rating": 2.5,
    "imgUrl": "https://exp.cdn-hotels.com/hotels/1000000/860000/855800/855741/855741_82_l.jpg"
  },
  {
    "price": 97,
    "name": "Pear Tree Inn Cape Girardeau Near the Medical Center",
    "address": "3248 William St, Cape Girardeau, MO, 63701 United States",
    "distance": 22.0,
    "rating": 4.0,
    "imgUrl": "https://exp.cdn-hotels.com/hotels/1000000/50000/40200/40113/40113_62_l.jpg"
  },
  {
    "price": 159,
    "name": "Hampton Inn Cape Girardeau I 55 East",
    "address": "207 S Mt Auburn Rd, Cape Girardeau, MO, 63703 United States",
    "distance": 22.0,
    "rating": 5.0,
    "imgUrl": "https://exp.cdn-hotels.com/hotels/13000000/12790000/12786700/12786627/12786627_1_l.jpg"
  }
]