[
  {
    "price": 94,
    "name": "Best Western Des Plaines Inn",
    "address": "1231 Lee St, Des Plaines, IL, 60018 United States",
    "distance": 0.3,
    "rating": 3.5,
    "imgUrl": "https://exp.cdn-hotels.com/hotels/1000000/610000/601700/601634/601634_165_l.jpg"
  },
  {
    "price": 82,
    "name": "Extended Stay America - Chicago - O\u0027Hare",
    "address": "1201 E Touhy Ave, Des Plaines, IL, 60018 United States",
    "distance": 1.8,
    "rating": 3.0,
    "imgUrl": "https://exp.cdn-hotels.com/hotels/1000000/110000/104200/104200/104200_29_l.jpg"
  },
  {
    "price": 81,
    "name": "Extended Stay America - Chicago- O\u0027Hare - Allstate Arena",
    "address": "1207 E Touhy Ave, Des Plaines, IL, 60018 United States",
    "distance": 1.8,
    "rating": 3.0,
    "imgUrl": "https://exp.cdn-hotels.com/hotels/1000000/160000/159000/158968/158968_22_l.jpg"
  },
  {
    "price": 133,
    "name": "Radisson Hotel Chicago O\u0027Hare",
    "address": "1450 E Touhy Ave, Des Plaines, IL, 60018 United States",
    "distance": 1.8,
    "rating": 4.0,
    "imgUrl": "https://exp.cdn-hotels.com/hotels/1000000/30000/22100/22075/22075_68_l.jpg"
  },
  {
    "price": 119,
    "name": "Comfort Inn O\u0027Hare - Convention Center",
    "address": "2175 E Touhy Ave, Des Plaines, IL, 60018 United States",
    "distance": 2.1,
    "rating": 3.5,
    "imgUrl": "https://exp.cdn-hotels.com/hotels/1000000/20000/11100/11013/11013_148_l.jpg"
  },
  {
    "price": 199,
    "name": "Hilton Garden Inn Chicago/O\u0027Hare Airport",
    "address": "2930 South River Road, Des Plaines, IL, 60018 United States",
    "distance": 2.8,
    "rating": 4.5,
    "imgUrl": "https://exp.cdn-hotels.com/hotels/2000000/1200000/1200000/1199960/1199960_12_l.jpg"
  },
  {
    "price": 151,
    "name": "Courtyard by Marriott Chicago O\u0027Hare",
    "address": "2950 S River Rd, Des Plaines, IL, 60018 United States",
    "distance": 2.9,
    "rating": 4.0,
    "imgUrl": "https://exp.cdn-hotels.com/hotels/1000000/20000/17900/17810/3cce49f4_l.jpg"
  }
]