[
  {
    "price": 140,
    "name": "Hampton Inn \u0026 Suites Alexandria",
    "address": "2705 S Broadway St, Alexandria, MN, 56308 United States",
    "distance": 1.3,
    "rating": 4.5,
    "imgUrl": "https://exp.cdn-hotels.com/hotels/2000000/1880000/1876400/1876343/1876343_50_l.jpg"
  },
  {
    "price": 107,
    "name": "AmericInn Lodge \u0026 Suites Alexandria",
    "address": "4520 Highway 29 S, Alexandria, MN, 56308 United States",
    "distance": 2.6,
    "rating": 4.0,
    "imgUrl": "https://exp.cdn-hotels.com/hotels/1000000/60000/50600/50507/15a215e2_l.jpg"
  },
  {
    "price": 71,
    "name": "Super 8 Alexandria MN",
    "address": "4620 Highway 29 S, Alexandria, MN, 56308 United States",
    "distance": 2.7,
    "rating": 4.0,
    "imgUrl": "https://exp.cdn-hotels.com/hotels/1000000/900000/892800/892758/892758_143_l.jpg"
  },
  {
    "price": 97,
    "name": "Best Western Alexandria Inn",
    "address": "508 Twin Blvd, Alexandria, MN, 56308 United States",
    "distance": 2.8,
    "rating": 4.0,
    "imgUrl": "https://exp.cdn-hotels.com/hotels/1000000/10000/8500/8499/8499_122_l.jpg"
  },
  {
    "price": 76,
    "name": "Days Inn Alexandria",
    "address": "4810 Highway 29 South, I-94 \u0026 Hwy 29 South, Alexandria, MN, 56308-2907 United States",
    "distance": 2.8,
    "rating": 2.5,
    "imgUrl": "https://exp.cdn-hotels.com/hotels/1000000/30000/21900/21832/608eb376_l.jpg"
  },
  {
    "price": 124,
    "name": "Arrowwood Resort and Conference Center",
    "address": "2100 Arrowwood Lane NW, Alexandria, MN, 56308 United States",
    "distance": 2.9,
    "rating": 3.5,
    "imgUrl": "https://exp.cdn-hotels.com/hotels/8000000/7880000/7875500/7875419/7875419_14_l.jpg"
  },
  {
    "price": 84,
    "name": "Country Inn \u0026 Suites By Carlson Alexandria",
    "address": "5304 Highway 29 S, Alexandria, MN, 56308 United States",
    "distance": 3.3,
    "rating": 3.5,
    "imgUrl": "https://exp.cdn-hotels.com/hotels/1000000/60000/59600/59525/7aec5115_l.jpg"
  },
  {
    "price": 118,
    "name": "Holiday Inn Alexandria",
    "address": "5637 Highway 29 South, Alexandria, MN, 56308 United States",
    "distance": 3.3,
    "rating": 3.0,
    "imgUrl": "https://exp.cdn-hotels.com/hotels/1000000/10000/8600/8537/8537_216_l.jpg"
  },
  {
    "price": 124,
    "name": "GrandStay Hotel \u0026 Suites",
    "address": "114 West Minnesota Avenue, Glenwood, MN, 56334 United States",
    "distance": 16.0,
    "rating": 4.5,
    "imgUrl": "https://exp.cdn-hotels.com/hotels/10000000/9050000/9048700/9048608/9048608_37_l.jpg"
  },
  {
    "price": 83,
    "name": "Americas Best Value Inn",
    "address": "340 County Road 21 South, Glenwood, MN, 56334 United States",
    "distance": 17.0,
    "rating": 4.5,
    "imgUrl": "https://exp.cdn-hotels.com/hotels/7000000/6120000/6113400/6113331/6113331_79_l.jpg"
  }
]