[
  {
    "price": 112,
    "name": "Country Inn \u0026 Suites by Carlson Rock Falls",
    "address": "2106 First Avenue, Rock Falls, IL, 61071 United States",
    "distance": 0.4,
    "rating": 4.5,
    "imgUrl": "https://exp.cdn-hotels.com/hotels/1000000/430000/422900/422852/422852_48_l.jpg"
  },
  {
    "price": 72,
    "name": "Super 8 Rock Falls Sterling Area",
    "address": "2100 1st Ave, Rock Falls, IL, 61071 United States",
    "distance": 0.4,
    "rating": 3.0,
    "imgUrl": "https://exp.cdn-hotels.com/hotels/1000000/50000/49600/49574/716f814c_l.jpg"
  },
  {
    "price": 110,
    "name": "Holiday Inn Express \u0026 Suites Rock Falls",
    "address": "301 E 2nd St, Rock Falls, IL, 61071 United States",
    "distance": 1.7,
    "rating": 4.5,
    "imgUrl": "https://exp.cdn-hotels.com/hotels/14000000/13400000/13399800/13399767/f670221c_l.jpg"
  }
]