[
  {
    "price": 93,
    "name": "Best Western Plus Fairburn Atlanta Southwest",
    "address": "1005 Oakley Industrial Blvd, Fairburn, GA, 30213 United States",
    "distance": 8.4,
    "rating": 4.5,
    "imgUrl": "https://exp.cdn-hotels.com/hotels/2000000/1680000/1674800/1674703/1674703_70_l.jpg"
  },
  {
    "price": 126,
    "name": "Holiday Inn Express Hotel \u0026 Suites Fairburn",
    "address": "7905 Senoia Rd., Fairburn, GA, 30213 United States",
    "distance": 8.4,
    "rating": 4.5,
    "imgUrl": "https://exp.cdn-hotels.com/hotels/3000000/2220000/2219800/2219768/2219768_139_l.jpg"
  },
  {
    "price": 80,
    "name": "Wingate by Wyndham Atlanta Airport Fairburn",
    "address": "7882 Senoia Road, Fairburn, GA, 30213 United States",
    "distance": 8.5,
    "rating": 4.0,
    "imgUrl": "https://exp.cdn-hotels.com/hotels/2000000/1510000/1507600/1507588/1507588_301_l.jpg"
  },
  {
    "price": 94,
    "name": "Country Inn \u0026 Suites By Carlson, Fairburn, GA",
    "address": "7815 Senoia Rd, Fairburn, GA, 30213 United States",
    "distance": 8.5,
    "rating": 3.5,
    "imgUrl": "https://exp.cdn-hotels.com/hotels/2000000/1880000/1874100/1874019/1874019_55_l.jpg"
  },
  {
    "price": 107,
    "name": "Hampton Inn Atlanta Fairburn",
    "address": "7790 Ella Ln, Fairburn, GA, 30213 United States",
    "distance": 8.6,
    "rating": 4.0,
    "imgUrl": "https://exp.cdn-hotels.com/hotels/2000000/1330000/1322000/1321939/1321939_40_l.jpg"
  },
  {
    "price": 85,
    "name": "Quality Inn Newnan",
    "address": "40 Lakeside Way, Newnan, GA, 30265 United States",
    "distance": 10.0,
    "rating": 4.0,
    "imgUrl": "https://exp.cdn-hotels.com/hotels/1000000/580000/571000/570928/0eaef56e_l.jpg"
  },
  {
    "price": 60,
    "name": "Motel 6 Newnan, GA",
    "address": "6 Herring Road, Newnan, GA, 30265 United States",
    "distance": 10.0,
    "rating": 2.0,
    "imgUrl": "https://exp.cdn-hotels.com/hotels/2000000/1040000/1037800/1037748/1037748_71_l.jpg"
  },
  {
    "price": 106,
    "name": "Holiday Inn Express Atlanta SW - Newnan",
    "address": "4 Herring Rd, Newnan, GA, 30265 United States",
    "distance": 10.0,
    "rating": 4.5,
    "imgUrl": "https://exp.cdn-hotels.com/hotels/13000000/12520000/12512300/12512214/12512214_14_l.jpg"
  },
  {
    "price": 121,
    "name": "Hampton Inn Atlanta - Newnan",
    "address": "50 Hampton Way, Newnan, GA, 30265 United States",
    "distance": 10.0,
    "rating": 4.0,
    "imgUrl": "https://exp.cdn-hotels.com/hotels/1000000/50000/42300/42257/42257_30_l.jpg"
  },
  {
    "price": 75,
    "name": "Best Western Shenandoah Inn",
    "address": "620 Highway 34 E, Newnan, GA, 30265 United States",
    "distance": 10.0,
    "rating": 4.0,
    "imgUrl": "https://exp.cdn-hotels.com/hotels/1000000/20000/14300/14279/14279_73_l.jpg"
  }
]